my_test_tuxpkg_project/__init__.py
my_test_tuxpkg_project/__main__.py
my_test_tuxpkg_project-0.22.0.dist-info/entry_points.txt
my_test_tuxpkg_project-0.22.0.dist-info/licenses/LICENSE
my_test_tuxpkg_project-0.22.0.dist-info/WHEEL
my_test_tuxpkg_project-0.22.0.dist-info/METADATA
my_test_tuxpkg_project-0.22.0.dist-info/RECORD
