Metadata-Version: 2.4
Name: my_test_tuxpkg_project
Version: 0.22.0
Summary: my-test-tuxpkg-project is ...
Author-email: Anders Roxell <anders.roxell@linaro.org>
Classifier: License :: OSI Approved :: MIT License
License-File: LICENSE
Project-URL: Home, https://github.com/roxell/my-test-tuxpkg-project
